Metadata-Version: 2.1
Name: fnv-c
Version: 0.2.0
Summary: Python 3.7+ FNV (fnv0, fnv1, fnv1a) non-cryptographic hash library implemented in C through libffi
Home-page: https://github.com/botify-labs/fnv-c
Author: Fabien MARTY
Author-email: fabien.marty@botify.com
License: UNKNOWN
Platform: UNKNOWN
Classifier: Development Status :: 4 - Beta
Classifier: Programming Language :: Python :: 3
Classifier: Programming Language :: Python :: Implementation :: PyPy
Classifier: License :: OSI Approved :: MIT License
